[
  {
    "key": "home",
    "name": "home",
    "a-icon": "home",
    "link": "/",
    "items": []
  },
  {
    "key": "dashboard",
    "name": "dashboard",
    "a-icon": "dashboard",
    "link": "/dashboard",
    "items": []
  },
  {
    "key": "expiration_soon",
    "name": "expiration_soon",
    "a-icon": "calendar",
    "link": "/expiration_soon",
    "items": []
  },
  {
    "key": "category",
    "name": "category",
    "a-icon": "appstore",
    "link": "/category",
    "items": []
  }
]
